htmldiff2.py
htmldiff2-0.2.2.dist-info/LICENSE
htmldiff2-0.2.2.dist-info/METADATA
htmldiff2-0.2.2.dist-info/WHEEL
htmldiff2-0.2.2.dist-info/top_level.txt
htmldiff2-0.2.2.dist-info/RECORD
