Metadata-Version: 2.1
Name: htmldiff2
Version: 0.2.2
Summary: Diffs arbitrary HTML inline.
License: Some rights reserved.
Requires-Python: >=2.7
License-File: LICENSE
Requires-Dist: genshi
Requires-Dist: html5lib
